LICENSE
MANIFEST.in
README.md
setup.py
djangoshop_paypal.egg-info/PKG-INFO
djangoshop_paypal.egg-info/SOURCES.txt
djangoshop_paypal.egg-info/dependency_links.txt
djangoshop_paypal.egg-info/not-zip-safe
djangoshop_paypal.egg-info/requires.txt
djangoshop_paypal.egg-info/top_level.txt
shop_paypal/__init__.py
shop_paypal/models.py
shop_paypal/modifiers.py
shop_paypal/payment.py
shop_paypal/locale/de/LC_MESSAGES/django.mo
shop_paypal/locale/de/LC_MESSAGES/django.po