Metadata-Version: 1.1
Name: djangoshop-paypal
Version: 0.1.4
Summary: PayPal Payment Provider Integration for django-shop
Home-page: https://github.com/jrief/djangoshop-paypal
Author: Jacob Rief
Author-email: jacob.rief@gmail.com
License: MIT License
Platform: OS Independent
Classifier: Environment :: Web Environment
Classifier: Framework :: Django
Classifier: Intended Audience :: Developers
Classifier: License :: OSI Approved :: MIT License
Classifier: Operating System :: OS Independent
Classifier: Programming Language :: Python
Classifier: Topic :: Software Development :: Libraries :: Application Frameworks
Classifier: Topic :: Internet :: WWW/HTTP :: Dynamic Content
